fedllm/__init__.py
fedllm/main.py
fedllm/component/__init__.py
fedllm/component/aggreagtor.py
fedllm/component/communicator.py
fedllm/component/trainer.py
fedllm/modal_hub/__init__.py
fedllm-0.0.1a0.dist-info/LICENSE
fedllm-0.0.1a0.dist-info/METADATA
fedllm-0.0.1a0.dist-info/WHEEL
fedllm-0.0.1a0.dist-info/top_level.txt
fedllm-0.0.1a0.dist-info/RECORD
