Metadata-Version: 2.1
Name: fedllm
Version: 0.0.1a0
Summary: FedLLM: A Federated Learning Library for Large Language Models.
Home-page: http://github.com/beiyuouo/FedLLM
Author: Bingjie Yan
Author-email: bj.yan.pa@qq.com
License: Apache-2.0 License
Keywords: configuration,config
Requires-Python: >=3.6
License-File: LICENSE
Requires-Dist: torch >=1.6.0
